streambox/__init__.py
streambox/__pycache__/__init__.cpython-39.pyc
streambox/decorators/__init__.py
streambox/decorators/cache.py
streambox/decorators/email_on_failure.py
streambox/decorators/logger.py
streambox/decorators/retry.py
streambox/decorators/timer.py
streambox/decorators/__pycache__/__init__.cpython-39.pyc
streambox/decorators/__pycache__/cache.cpython-39.pyc
streambox/decorators/__pycache__/email_on_failure.cpython-39.pyc
streambox/decorators/__pycache__/logger.cpython-39.pyc
streambox/decorators/__pycache__/retry.cpython-39.pyc
streambox/decorators/__pycache__/timer.cpython-39.pyc
streambox/lib/__init__.py
streambox/lib/email.py
streambox/lib/streamlit_import.py
streambox/lib/streamlit_server.py
streambox/lib/__pycache__/__init__.cpython-39.pyc
streambox/lib/__pycache__/email.cpython-39.pyc
streambox/lib/__pycache__/streamlit_import.cpython-39.pyc
streambox/lib/__pycache__/streamlit_server.cpython-39.pyc
streambox/streamlit/__init__.py
streambox/streamlit/session.py
streambox/streamlit/style.py
streambox/streamlit/__pycache__/__init__.cpython-39.pyc
streambox/streamlit/__pycache__/session.cpython-39.pyc
streambox/streamlit/__pycache__/style.cpython-39.pyc
streambox-0.0.2.dist-info/LICENSE
streambox-0.0.2.dist-info/METADATA
streambox-0.0.2.dist-info/WHEEL
streambox-0.0.2.dist-info/top_level.txt
streambox-0.0.2.dist-info/RECORD
