Metadata-Version: 2.1
Name: streambox
Version: 0.0.2
Summary: A package for generic data science utilities
Author-email: Kaveh Bakhtiyari <kbakhtiyari@yahoo.com>
Project-URL: Homepage, https://github.com/kavehbc/streambox
Project-URL: Bug Tracker, https://github.com/kavehbc/streambox
Classifier: Programming Language :: Python :: 3
Classifier: License :: OSI Approved :: MIT License
Classifier: Operating System :: OS Independent
Requires-Python: >=3.8
License-File: LICENSE
Requires-Dist: pandas (==1.5.3)
Requires-Dist: streamlit (==1.20.0)
Requires-Dist: timeutils (==0.3.2)
